src/API.py
src/__init__.py
src/__main__.py
src/data.py
src/interface.py
src/main.py
src/offline_model.py
src/parser.py
src/scheduler.py
src/task.py
carbon_aware_scheduler-1.0.2.dist-info/LICENSE.txt
carbon_aware_scheduler-1.0.2.dist-info/METADATA
carbon_aware_scheduler-1.0.2.dist-info/WHEEL
carbon_aware_scheduler-1.0.2.dist-info/entry_points.txt
carbon_aware_scheduler-1.0.2.dist-info/top_level.txt
carbon_aware_scheduler-1.0.2.dist-info/RECORD
