Metadata-Version: 2.1
Name: carbon-aware-scheduler
Version: 1.0.2
Summary: Carbon-minimizing task scheduler for Unix systems
Home-page: https://github.com/abel-vs/carbon-scheduler
Author: Wander Siemers, Abel van Steenweghen, Florentin Arsene
Author-email: wandersiemers@me.com
License: MIT
Platform: UNKNOWN
Classifier: License :: OSI Approved :: MIT License
Classifier: Programming Language :: Python :: 3
Classifier: Programming Language :: Python :: 3.10
License-File: LICENSE.txt
Requires-Dist: numpy
Requires-Dist: pandas
Requires-Dist: requests
Requires-Dist: python-crontab
Requires-Dist: croniter
Requires-Dist: pyinquirer
